sqler/__init__.py
sqler/adapter/__init__.py
sqler/adapter/abstract.py
sqler/adapter/asynchronous.py
sqler/adapter/synchronous.py
sqler/cache.py
sqler/db/__init__.py
sqler/db/async_db.py
sqler/db/sqler_db.py
sqler/exceptions.py
sqler/export.py
sqler/fts.py
sqler/logging.py
sqler/metrics.py
sqler/migrations.py
sqler/models/__init__.py
sqler/models/async_integrity.py
sqler/models/async_model.py
sqler/models/async_queryset.py
sqler/models/async_safe.py
sqler/models/integrity.py
sqler/models/mixins.py
sqler/models/model.py
sqler/models/model_field.py
sqler/models/queryset.py
sqler/models/ref.py
sqler/models/safe.py
sqler/models/utils.py
sqler/ops.py
sqler/pool.py
sqler/py.typed
sqler/query/__init__.py
sqler/query/async_query.py
sqler/query/expression.py
sqler/query/field.py
sqler/query/query.py
sqler/registry.py
sqler/tracking.py
sqler/utils.py
sqler-1.2026.1.5.dist-info/WHEEL
sqler-1.2026.1.5.dist-info/METADATA
sqler-1.2026.1.5.dist-info/RECORD
