Metadata-Version: 2.3
Name: sqler
Version: 1.2026.1.5
Summary: Micro-ORM with Pydantic model persistence
Requires-Dist: aiosqlite>=0.21.0
Requires-Dist: pydantic>=2.10.0
Requires-Python: >=3.12
